[
  {
    "id": "optic_reddot",
    "name_cn": "红点瞄具",
    "slot": "optic",
    "compatible": [
      "突击步枪",
      "冲锋枪",
      "精确射手步枪",
      "战斗步枪",
      "紧凑突击步枪",
      "霰弹枪"
    ],
    "stat_mods": {
      "accuracy": 5,
      "mobility": -1
    },
    "price": 5665,
    "price_source": "实测参考反射式瞄具价格区间",
    "tags": [
      "近战"
    ]
  },
  {
    "id": "optic_holo",
    "name_cn": "全息瞄具",
    "slot": "optic",
    "compatible": [
      "突击步枪",
      "冲锋枪",
      "精确射手步枪",
      "战斗步枪",
      "紧凑突击步枪"
    ],
    "stat_mods": {
      "accuracy": 7,
      "mobility": -2
    },
    "price": 5664,
    "price_source": "实测参考全息瞄具价格区间",
    "tags": [
      "全能"
    ]
  },
  {
    "id": "optic_4x",
    "name_cn": "ACOG 4倍瞄具",
    "slot": "optic",
    "compatible": [
      "突击步枪",
      "精确射手步枪",
      "战斗步枪",
      "狙击步枪"
    ],
    "stat_mods": {
      "accuracy": 8,
      "range": 5,
      "mobility": -3
    },
    "price": 45373,
    "price_source": "实测：ACOG精准六倍镜",
    "tags": [
      "高倍镜"
    ]
  },
  {
    "id": "optic_8x",
    "name_cn": "8倍狙击瞄具",
    "slot": "optic",
    "compatible": [
      "狙击步枪",
      "精确射手步枪",
      "战斗步枪"
    ],
    "stat_mods": {
      "accuracy": 10,
      "range": 8,
      "mobility": -5,
      "handling": -3
    },
    "price": 11996,
    "price_source": "实测：PSO狙击8倍瞄准镜",
    "tags": [
      "狙击"
    ]
  },
  {
    "id": "optic_none",
    "name_cn": "无瞄具（机械准星）",
    "slot": "optic",
    "compatible": [
      "突击步枪",
      "冲锋枪",
      "精确射手步枪",
      "战斗步枪",
      "紧凑突击步枪",
      "霰弹枪",
      "轻机枪",
      "通用机枪",
      "狙击步枪"
    ],
    "stat_mods": {
      "mobility": 2,
      "handling": 1
    },
    "price": 0,
    "price_source": "机械准星，武器自带",
    "tags": [
      "零成本"
    ]
  },
  {
    "id": "barrel_short",
    "name_cn": "短枪管",
    "slot": "barrel",
    "compatible": [
      "突击步枪",
      "冲锋枪",
      "精确射手步枪",
      "战斗步枪",
      "紧凑突击步枪",
      "霰弹枪"
    ],
    "stat_mods": {
      "mobility": 4,
      "handling": 3,
      "range": -5,
      "damage": -2
    },
    "price": 101377,
    "price_source": "实测：93R实用轻枪管",
    "tags": [
      "近战"
    ],
    "price_3d": 101377,
    "price_7d": 102362,
    "price_30d": 103347
  },
  {
    "id": "barrel_standard",
    "name_cn": "标准枪管",
    "slot": "barrel",
    "compatible": [
      "突击步枪",
      "冲锋枪",
      "精确射手步枪",
      "战斗步枪",
      "紧凑突击步枪",
      "霰弹枪",
      "轻机枪",
      "通用机枪"
    ],
    "stat_mods": {},
    "price": 37214,
    "price_source": "无属性惩罚，默认免费",
    "tags": [
      "平衡"
    ],
    "price_3d": 37214,
    "price_7d": 52634,
    "price_30d": 37214
  },
  {
    "id": "barrel_long",
    "name_cn": "长枪管",
    "slot": "barrel",
    "compatible": [
      "突击步枪",
      "精确射手步枪",
      "战斗步枪",
      "狙击步枪",
      "轻机枪",
      "通用机枪"
    ],
    "stat_mods": {
      "range": 8,
      "accuracy": 3,
      "mobility": -4,
      "handling": -2
    },
    "price": 41067,
    "price_source": "实测：QBZ95战术枪管",
    "tags": [
      "远距离"
    ],
    "price_3d": 41067,
    "price_7d": 74477,
    "price_30d": 37212
  },
  {
    "id": "barrel_heavy",
    "name_cn": "重枪管",
    "slot": "barrel",
    "compatible": [
      "突击步枪",
      "精确射手步枪",
      "战斗步枪",
      "轻机枪",
      "通用机枪"
    ],
    "stat_mods": {
      "accuracy": 6,
      "control": 5,
      "mobility": -6,
      "handling": -3
    },
    "price": 34804,
    "price_source": "实测：93R实用重枪管",
    "tags": [
      "稳定"
    ]
  },
  {
    "id": "barrel_integrated_supp",
    "name_cn": "集成消音枪管",
    "slot": "barrel",
    "compatible": [
      "突击步枪",
      "冲锋枪",
      "紧凑突击步枪"
    ],
    "stat_mods": {
      "accuracy": 3,
      "mobility": 2,
      "damage": -1
    },
    "price": 15000,
    "price_source": "估算：消音+枪管综合价格区间",
    "tags": [
      "隐蔽"
    ]
  },
  {
    "id": "stock_none",
    "name_cn": "无枪托",
    "slot": "stock",
    "compatible": [
      "突击步枪",
      "冲锋枪",
      "精确射手步枪",
      "战斗步枪",
      "紧凑突击步枪",
      "霰弹枪"
    ],
    "stat_mods": {
      "mobility": 5,
      "handling": 4,
      "control": -5
    },
    "price": 0,
    "price_source": "无枪托，武器自带",
    "tags": [
      "近战"
    ]
  },
  {
    "id": "stock_light",
    "name_cn": "轻型枪托",
    "slot": "stock",
    "compatible": [
      "突击步枪",
      "冲锋枪",
      "精确射手步枪",
      "战斗步枪",
      "紧凑突击步枪"
    ],
    "stat_mods": {
      "mobility": 3,
      "handling": 3,
      "control": -2
    },
    "price": 20551,
    "price_source": "实测：UZI枪托",
    "tags": [
      "机动"
    ]
  },
  {
    "id": "stock_standard",
    "name_cn": "标准枪托",
    "slot": "stock",
    "compatible": [
      "突击步枪",
      "精确射手步枪",
      "战斗步枪",
      "狙击步枪",
      "轻机枪",
      "通用机枪"
    ],
    "stat_mods": {
      "control": 4,
      "accuracy": 2
    },
    "price": 5639,
    "price_source": "实测：M4缓冲托芯",
    "tags": [
      "全能"
    ]
  },
  {
    "id": "stock_folding",
    "name_cn": "折叠枪托",
    "slot": "stock",
    "compatible": [
      "突击步枪",
      "冲锋枪",
      "紧凑突击步枪",
      "霰弹枪"
    ],
    "stat_mods": {
      "mobility": 4,
      "handling": 5,
      "control": -3
    },
    "price": 22986,
    "price_source": "实测：MP5伸缩枪托",
    "tags": [
      "机动"
    ]
  },
  {
    "id": "grip_none",
    "name_cn": "无握把",
    "slot": "grip",
    "compatible": [
      "突击步枪",
      "冲锋枪",
      "精确射手步枪",
      "战斗步枪",
      "紧凑突击步枪",
      "霰弹枪",
      "轻机枪",
      "通用机枪",
      "狙击步枪"
    ],
    "stat_mods": {},
    "price": 0,
    "price_source": "无握把，武器自带",
    "tags": [
      "零成本"
    ]
  },
  {
    "id": "grip_vertical",
    "name_cn": "垂直握把",
    "slot": "grip",
    "compatible": [
      "突击步枪",
      "精确射手步枪",
      "战斗步枪",
      "轻机枪",
      "通用机枪"
    ],
    "stat_mods": {
      "control": 6,
      "accuracy": 3,
      "mobility": -2
    },
    "price": 69323,
    "price_source": "实测：实用垂直握把",
    "tags": [
      "稳定"
    ]
  },
  {
    "id": "grip_angled",
    "name_cn": "角度握把",
    "slot": "grip",
    "compatible": [
      "突击步枪",
      "冲锋枪",
      "精确射手步枪",
      "战斗步枪",
      "紧凑突击步枪"
    ],
    "stat_mods": {
      "control": 4,
      "mobility": 1,
      "handling": 2
    },
    "price": 3722,
    "price_source": "实测参考：战术/竞技握把价格区间",
    "tags": [
      "全能"
    ]
  },
  {
    "id": "grip_light",
    "name_cn": "轻便握把",
    "slot": "grip",
    "compatible": [
      "突击步枪",
      "冲锋枪",
      "紧凑突击步枪",
      "霰弹枪"
    ],
    "stat_mods": {
      "mobility": 4,
      "handling": 3,
      "control": -3
    },
    "price": 3549,
    "price_source": "实测：M7稳定后握把",
    "tags": [
      "近战"
    ]
  },
  {
    "id": "mag_standard",
    "name_cn": "标准弹匣",
    "slot": "magazine",
    "compatible": [
      "突击步枪",
      "冲锋枪",
      "精确射手步枪",
      "战斗步枪",
      "紧凑突击步枪",
      "轻机枪",
      "通用机枪",
      "狙击步枪",
      "射手步枪"
    ],
    "stat_mods": {},
    "price": 0,
    "price_source": "标配弹匣，随枪附带",
    "tags": [
      "标准"
    ]
  },
  {
    "id": "mag_extended",
    "name_cn": "扩容弹匣",
    "slot": "magazine",
    "compatible": [
      "突击步枪",
      "冲锋枪",
      "精确射手步枪",
      "战斗步枪",
      "紧凑突击步枪",
      "狙击步枪",
      "射手步枪"
    ],
    "stat_mods": {
      "mobility": -2,
      "handling": -1
    },
    "price": 51432,
    "price_source": "实测参考：扩容弹匣价格区间",
    "tags": [
      "续航"
    ],
    "price_3d": 51432,
    "price_7d": 78057,
    "price_30d": 44332
  },
  {
    "id": "mag_drum",
    "name_cn": "弹鼓",
    "slot": "magazine",
    "compatible": [
      "突击步枪",
      "轻机枪",
      "通用机枪",
      "冲锋枪",
      "狙击步枪",
      "射手步枪"
    ],
    "stat_mods": {
      "mobility": -5,
      "handling": -3
    },
    "price": 53217,
    "price_source": "实测：野牛64发弹筒",
    "tags": [
      "大容量"
    ],
    "price_3d": 53217,
    "price_7d": 88717,
    "price_30d": 67417
  },
  {
    "id": "mag_fast",
    "name_cn": "快速弹匣",
    "slot": "magazine",
    "compatible": [
      "突击步枪",
      "冲锋枪",
      "精确射手步枪",
      "战斗步枪",
      "紧凑突击步枪",
      "霰弹枪",
      "狙击步枪",
      "射手步枪"
    ],
    "stat_mods": {
      "handling": 5,
      "mobility": 1
    },
    "price": 14880,
    "price_source": "实测：UZI 45发弹匣",
    "tags": [
      "快速"
    ]
  },
  {
    "id": "mag_small",
    "name_cn": "短弹匣",
    "slot": "magazine",
    "compatible": [
      "突击步枪",
      "冲锋枪",
      "紧凑突击步枪",
      "狙击步枪",
      "射手步枪"
    ],
    "stat_mods": {
      "mobility": 3,
      "handling": 2
    },
    "price": 3532,
    "price_source": "实测：AKS74U 30发弹匣",
    "tags": [
      "隐蔽"
    ]
  },
  {
    "id": "muzzle_none",
    "name_cn": "无枪口装置",
    "slot": "muzzle",
    "compatible": [
      "突击步枪",
      "冲锋枪",
      "精确射手步枪",
      "战斗步枪",
      "紧凑突击步枪",
      "霰弹枪",
      "轻机枪",
      "通用机枪",
      "狙击步枪"
    ],
    "stat_mods": {
      "mobility": 1
    },
    "price": 0,
    "price_source": "无枪口装置，武器自带",
    "tags": [
      "零成本"
    ]
  },
  {
    "id": "muzzle_suppressor",
    "name_cn": "消音器",
    "slot": "muzzle",
    "compatible": [
      "突击步枪",
      "冲锋枪",
      "精确射手步枪",
      "战斗步枪",
      "紧凑突击步枪",
      "狙击步枪"
    ],
    "stat_mods": {
      "accuracy": 5,
      "range": 3,
      "mobility": -1
    },
    "price": 51676,
    "price_source": "实测：OPS消音器 / 实用消音器",
    "tags": [
      "隐蔽"
    ],
    "price_3d": 51676,
    "price_7d": 71311,
    "price_30d": 51676
  },
  {
    "id": "muzzle_brake",
    "name_cn": "制退器",
    "slot": "muzzle",
    "compatible": [
      "突击步枪",
      "精确射手步枪",
      "战斗步枪",
      "狙击步枪",
      "轻机枪",
      "通用机枪"
    ],
    "stat_mods": {
      "control": 8,
      "accuracy": 3,
      "mobility": -2
    },
    "price": 13587,
    "price_source": "实测：AK实用补偿器",
    "tags": [
      "稳定"
    ]
  },
  {
    "id": "muzzle_compensator",
    "name_cn": "补偿器",
    "slot": "muzzle",
    "compatible": [
      "突击步枪",
      "冲锋枪",
      "紧凑突击步枪",
      "霰弹枪"
    ],
    "stat_mods": {
      "control": 5,
      "accuracy": 4
    },
    "price": 44752,
    "price_source": "实测参考：制退器/消焰器价格区间",
    "tags": [
      "近战"
    ]
  },
  {
    "id": "laser_none",
    "name_cn": "无激光",
    "slot": "laser",
    "compatible": [
      "突击步枪",
      "冲锋枪",
      "精确射手步枪",
      "战斗步枪",
      "紧凑突击步枪",
      "霰弹枪",
      "轻机枪",
      "通用机枪",
      "狙击步枪"
    ],
    "stat_mods": {},
    "price": 0,
    "price_source": "无激光，武器自带",
    "tags": [
      "零成本"
    ]
  },
  {
    "id": "laser_red",
    "name_cn": "红色激光指示器",
    "slot": "laser",
    "compatible": [
      "突击步枪",
      "冲锋枪",
      "精确射手步枪",
      "战斗步枪",
      "紧凑突击步枪",
      "霰弹枪"
    ],
    "stat_mods": {
      "accuracy": 4,
      "mobility": 1
    },
    "price": 3500,
    "price_source": "估算参考：瞄具低价区间",
    "tags": [
      "近战"
    ]
  },
  {
    "id": "laser_ir",
    "name_cn": "红外激光（夜视兼容）",
    "slot": "laser",
    "compatible": [
      "突击步枪",
      "精确射手步枪",
      "战斗步枪",
      "狙击步枪",
      "紧凑突击步枪"
    ],
    "stat_mods": {
      "accuracy": 6,
      "range": 2
    },
    "price": 5500,
    "price_source": "估算参考：瞄具中价区间",
    "tags": [
      "战术"
    ]
  },
  {
    "id": "laser_flashlight",
    "name_cn": "战术手电",
    "slot": "laser",
    "compatible": [
      "突击步枪",
      "冲锋枪",
      "紧凑突击步枪",
      "霰弹枪"
    ],
    "stat_mods": {
      "mobility": -1
    },
    "price": 41667,
    "price_source": "估算参考：低价瞄具区间",
    "tags": [
      "近战"
    ]
  }
]