[
  {
    "id": "w1",
    "name_cn": "沙漠之鹰",
    "name_en": "Desert Eagle",
    "type": "手枪",
    "type_en": "Pistol",
    "mode": "both",
    "base_stats": {
      "damage": 65,
      "rate_of_fire": 300,
      "accuracy": 70,
      "range": 35,
      "control": 72,
      "mobility": 92,
      "handling": 88
    },
    "ammo_type": [
      ".50 AE"
    ],
    "meta_tier": "B",
    "unlock_level": 8,
    "game_id": 3,
    "copy_count": 1387,
    "tags": [
      "大口径"
    ],
    "loadout_price": 17640,
    "price": 17640,
    "custom_code": "6IK11K003KTK601F43COS",
    "price_3d": 17640,
    "price_7d": 17640,
    "price_30d": 17030
  },
  {
    "id": "w2",
    "name_cn": ".357左轮",
    "name_en": ".357 Revolver",
    "type": "手枪",
    "type_en": "Pistol",
    "mode": "both",
    "base_stats": {
      "damage": 78,
      "rate_of_fire": 180,
      "accuracy": 68,
      "range": 42,
      "control": 60,
      "mobility": 88,
      "handling": 78
    },
    "ammo_type": [
      ".357 Magnum"
    ],
    "meta_tier": "B",
    "unlock_level": 12,
    "game_id": 15,
    "copy_count": 3043,
    "tags": [
      "高伤害"
    ],
    "loadout_price": 13900,
    "price": 13900,
    "custom_code": "6G9423S08OPOB8QKQ72I8",
    "price_3d": 13900,
    "price_7d": 13150,
    "price_30d": 13900
  },
  {
    "id": "w3",
    "name_cn": "G17",
    "name_en": "G17",
    "type": "手枪",
    "type_en": "Pistol",
    "mode": "both",
    "base_stats": {
      "damage": 48,
      "rate_of_fire": 850,
      "accuracy": 72,
      "range": 28,
      "control": 80,
      "mobility": 95,
      "handling": 90
    },
    "ammo_type": [
      "9mm"
    ],
    "meta_tier": "C",
    "unlock_level": 1,
    "game_id": 59,
    "copy_count": 2490,
    "tags": [
      "新手"
    ],
    "loadout_price": 58,
    "price": 58,
    "custom_code": "6GDORHK02QIKBV894R7VJ",
    "price_3d": 58,
    "price_7d": 5000,
    "price_30d": 4800
  },
  {
    "id": "w4",
    "name_cn": "93R",
    "name_en": "93R",
    "type": "手枪",
    "type_en": "Pistol",
    "mode": "both",
    "base_stats": {
      "damage": 58,
      "rate_of_fire": 1100,
      "accuracy": 65,
      "range": 30,
      "control": 70,
      "mobility": 90,
      "handling": 85
    },
    "ammo_type": [
      "9mm"
    ],
    "meta_tier": "B",
    "unlock_level": 15,
    "game_id": 122,
    "copy_count": 1708,
    "tags": [
      "全自动手枪"
    ],
    "loadout_price": 1540,
    "price": 1540,
    "custom_code": "6GQG1O006S5HCI6L9NAJQ",
    "price_3d": 1540,
    "price_7d": 18085,
    "price_30d": 15885
  },
  {
    "id": "w5",
    "name_cn": "M1911",
    "name_en": "M1911",
    "type": "手枪",
    "type_en": "Pistol",
    "mode": "both",
    "base_stats": {
      "damage": 62,
      "rate_of_fire": 350,
      "accuracy": 74,
      "range": 32,
      "control": 78,
      "mobility": 92,
      "handling": 85
    },
    "ammo_type": [
      ".45 ACP"
    ],
    "meta_tier": "B",
    "unlock_level": 5,
    "game_id": 168,
    "copy_count": 4567,
    "tags": [
      "经典"
    ],
    "loadout_price": 784,
    "price": 784,
    "custom_code": "6IT12MG066MHHVC5Q80C6",
    "price_3d": 784,
    "price_7d": 17375,
    "price_30d": 17030
  },
  {
    "id": "w6",
    "name_cn": "QSZ92G",
    "name_en": "QSZ-92G",
    "type": "手枪",
    "type_en": "Pistol",
    "mode": "both",
    "base_stats": {
      "damage": 45,
      "rate_of_fire": 820,
      "accuracy": 76,
      "range": 30,
      "control": 82,
      "mobility": 94,
      "handling": 88
    },
    "ammo_type": [
      "9mm"
    ],
    "meta_tier": "C",
    "unlock_level": 1,
    "game_id": 212,
    "copy_count": 3836,
    "tags": [
      "标准配置"
    ],
    "loadout_price": 56,
    "price": 56,
    "custom_code": "6IT14U0066MHHVC5Q80C6",
    "price_3d": 56,
    "price_7d": 5000,
    "price_30d": 5000
  },
  {
    "id": "w7",
    "name_cn": "G18",
    "name_en": "G18",
    "type": "手枪",
    "type_en": "Pistol",
    "mode": "both",
    "base_stats": {
      "damage": 52,
      "rate_of_fire": 1200,
      "accuracy": 58,
      "range": 25,
      "control": 62,
      "mobility": 92,
      "handling": 86
    },
    "ammo_type": [
      "9mm"
    ],
    "meta_tier": "A",
    "unlock_level": 18,
    "game_id": 262,
    "copy_count": 4315,
    "tags": [
      "全自动"
    ],
    "loadout_price": 585,
    "price": 585,
    "custom_code": "6G941RG08OPOB8QKQ72I8",
    "price_3d": 585,
    "price_7d": 19112,
    "price_30d": 18725
  },
  {
    "id": "w8",
    "name_cn": "MP5冲锋枪",
    "name_en": "MP5 SMG",
    "type": "冲锋枪",
    "type_en": "Submachine Gun",
    "mode": "operations",
    "base_stats": {
      "damage": 45,
      "rate_of_fire": 900,
      "accuracy": 78,
      "range": 35,
      "control": 82,
      "mobility": 92,
      "handling": 90
    },
    "ammo_type": [
      "9mm"
    ],
    "meta_tier": "S",
    "unlock_level": 1,
    "game_id": 401,
    "copy_count": 3891,
    "tags": [
      "版本强势",
      "危险行动"
    ],
    "loadout_price": 52292,
    "price": 52292,
    "custom_code": "6H8OK3S0CN2U58NL2UJC9",
    "price_3d": 52292,
    "price_7d": 50752,
    "price_30d": 58452
  },
  {
    "id": "w9",
    "name_cn": "SMG-45冲锋枪",
    "name_en": "SMG-45",
    "type": "冲锋枪",
    "type_en": "Submachine Gun",
    "mode": "warfare",
    "base_stats": {
      "damage": 52,
      "rate_of_fire": 750,
      "accuracy": 72,
      "range": 40,
      "control": 75,
      "mobility": 88,
      "handling": 85
    },
    "ammo_type": [
      "9mm"
    ],
    "meta_tier": "B",
    "unlock_level": 8,
    "game_id": 364,
    "copy_count": 1336,
    "tags": [],
    "loadout_price": 53331,
    "price": 53331,
    "custom_code": "6HBE1RO079EV449EBAHBQ",
    "price_3d": 53331,
    "price_7d": 51806,
    "price_30d": 59431
  },
  {
    "id": "w10",
    "name_cn": "Vector冲锋枪",
    "name_en": "Vector SMG",
    "type": "冲锋枪",
    "type_en": "Submachine Gun",
    "mode": "warfare",
    "base_stats": {
      "damage": 48,
      "rate_of_fire": 1200,
      "accuracy": 65,
      "range": 30,
      "control": 70,
      "mobility": 95,
      "handling": 92
    },
    "ammo_type": [
      "9mm"
    ],
    "meta_tier": "A",
    "unlock_level": 15,
    "game_id": 510,
    "copy_count": 2206,
    "tags": [
      "版本强势",
      "全兵种"
    ],
    "loadout_price": 161655,
    "price": 161655,
    "custom_code": "6H135GK0FIOH9JJL4D8E6",
    "price_3d": 161655,
    "price_7d": 125150,
    "price_30d": 114720
  },
  {
    "id": "w11",
    "name_cn": "MP7冲锋枪",
    "name_en": "MP7 SMG",
    "type": "冲锋枪",
    "type_en": "Submachine Gun",
    "mode": "warfare",
    "base_stats": {
      "damage": 42,
      "rate_of_fire": 1000,
      "accuracy": 75,
      "range": 38,
      "control": 78,
      "mobility": 90,
      "handling": 88
    },
    "ammo_type": [
      "9mm"
    ],
    "meta_tier": "B",
    "unlock_level": 20,
    "game_id": 139,
    "copy_count": 2891,
    "tags": [],
    "loadout_price": 166870,
    "price": 166870,
    "custom_code": "6I6U22K04PC56TM4QFHON",
    "price_3d": 166870,
    "price_7d": 135580,
    "price_30d": 245095
  },
  {
    "id": "w12",
    "name_cn": "UZI冲锋枪",
    "name_en": "UZI SMG",
    "type": "冲锋枪",
    "type_en": "Submachine Gun",
    "mode": "warfare",
    "base_stats": {
      "damage": 44,
      "rate_of_fire": 1100,
      "accuracy": 60,
      "range": 28,
      "control": 65,
      "mobility": 96,
      "handling": 94
    },
    "ammo_type": [
      "9mm"
    ],
    "meta_tier": "C",
    "unlock_level": 5,
    "game_id": 485,
    "copy_count": 3481,
    "tags": [],
    "loadout_price": 12055,
    "price": 12055,
    "custom_code": "6HGJBO80APGGNCBFQNVEF",
    "price_3d": 12055,
    "price_7d": 12055,
    "price_30d": 12055
  },
  {
    "id": "w13",
    "name_cn": "SR-3M突击步枪",
    "name_en": "SR-3M Compact",
    "type": "突击步枪",
    "type_en": "Assault Rifle",
    "mode": "operations",
    "base_stats": {
      "damage": 52,
      "rate_of_fire": 950,
      "accuracy": 62,
      "range": 32,
      "control": 58,
      "mobility": 93,
      "handling": 90
    },
    "ammo_type": [
      "9mm"
    ],
    "meta_tier": "A",
    "unlock_level": 28,
    "game_id": 294,
    "copy_count": 347,
    "tags": [],
    "loadout_price": 121143,
    "price": 121143,
    "custom_code": "6GS6MS006U3GLSPD6DRKM",
    "price_3d": 121143,
    "price_7d": 87813,
    "price_30d": 130233
  },
  {
    "id": "w14",
    "name_cn": "QCQ171冲锋枪",
    "name_en": "QCQ-171 SMG",
    "type": "冲锋枪",
    "type_en": "Submachine Gun",
    "mode": "operations",
    "base_stats": {
      "damage": 50,
      "rate_of_fire": 800,
      "accuracy": 74,
      "range": 38,
      "control": 78,
      "mobility": 86,
      "handling": 82
    },
    "ammo_type": [
      "9mm"
    ],
    "meta_tier": "A",
    "unlock_level": 22,
    "game_id": 50,
    "copy_count": 4391,
    "tags": [
      "国产"
    ],
    "loadout_price": 133263,
    "price": 133263,
    "custom_code": "6GV4DOS03I0RFPFTOIP1D",
    "price_3d": 133263,
    "price_7d": 115083,
    "price_30d": 115083
  },
  {
    "id": "w15",
    "name_cn": "P90冲锋枪",
    "name_en": "P90 SMG",
    "type": "冲锋枪",
    "type_en": "Submachine Gun",
    "mode": "both",
    "base_stats": {
      "damage": 42,
      "rate_of_fire": 898,
      "accuracy": 58,
      "range": 28,
      "control": 55,
      "mobility": 94,
      "handling": 88
    },
    "ammo_type": [
      "9mm"
    ],
    "meta_tier": "S",
    "unlock_level": 20,
    "game_id": 339,
    "copy_count": 201,
    "tags": [
      "大弹容",
      "危险行动"
    ],
    "loadout_price": 82305,
    "price": 82305,
    "custom_code": "6EHRS780C6U07V9G7JRFB",
    "price_3d": 82305,
    "price_7d": 76205,
    "price_30d": 94505
  },
  {
    "id": "w16",
    "name_cn": "勇士冲锋枪",
    "name_en": "Vityaz SMG",
    "type": "冲锋枪",
    "type_en": "Submachine Gun",
    "mode": "warfare",
    "base_stats": {
      "damage": 46,
      "rate_of_fire": 780,
      "accuracy": 70,
      "range": 34,
      "control": 76,
      "mobility": 90,
      "handling": 84
    },
    "ammo_type": [
      "9mm"
    ],
    "meta_tier": "B",
    "unlock_level": 12,
    "game_id": 353,
    "copy_count": 1621,
    "tags": [
      "国产"
    ],
    "loadout_price": 50235,
    "price": 50235,
    "custom_code": "6GS6O1K06U3GLSPD6DRKM",
    "price_3d": 50235,
    "price_7d": 48710,
    "price_30d": 53285
  },
  {
    "id": "w17",
    "name_cn": "野牛冲锋枪",
    "name_en": "Bizon SMG",
    "type": "冲锋枪",
    "type_en": "Submachine Gun",
    "mode": "both",
    "base_stats": {
      "damage": 47,
      "rate_of_fire": 720,
      "accuracy": 66,
      "range": 36,
      "control": 74,
      "mobility": 88,
      "handling": 80
    },
    "ammo_type": [
      "9mm"
    ],
    "meta_tier": "B",
    "unlock_level": 10,
    "game_id": 509,
    "copy_count": 2947,
    "tags": [
      "大弹容"
    ],
    "loadout_price": 12101,
    "price": 12101,
    "custom_code": "6HGJDDK0APGGNCBFQNVEF",
    "price_3d": 12101,
    "price_7d": 12101,
    "price_30d": 12101
  },
  {
    "id": "w19",
    "name_cn": "M870霰弹枪",
    "name_en": "M870 Shotgun",
    "type": "霰弹枪",
    "type_en": "Shotgun",
    "mode": "both",
    "base_stats": {
      "damage": 92,
      "rate_of_fire": 80,
      "accuracy": 35,
      "range": 22,
      "control": 58,
      "mobility": 82,
      "handling": 68
    },
    "ammo_type": [
      "12-gauge"
    ],
    "meta_tier": "A",
    "unlock_level": 15,
    "game_id": 140,
    "copy_count": 394,
    "tags": [
      "泵动",
      "高伤害"
    ],
    "loadout_price": 5000,
    "price": 5000,
    "custom_code": "6JQT26402FA1JF0E0BJHI",
    "price_3d": 5000,
    "price_7d": 5000,
    "price_30d": 5000
  },
  {
    "id": "w20",
    "name_cn": "S12K霰弹枪",
    "name_en": "S12K Shotgun",
    "type": "霰弹枪",
    "type_en": "Shotgun",
    "mode": "warfare",
    "base_stats": {
      "damage": 90,
      "rate_of_fire": 450,
      "accuracy": 40,
      "range": 20,
      "control": 55,
      "mobility": 80,
      "handling": 78
    },
    "ammo_type": [
      "12-gauge"
    ],
    "meta_tier": "B",
    "unlock_level": 10,
    "game_id": 422,
    "copy_count": 2641,
    "tags": [
      "近战",
      "推荐配装"
    ],
    "loadout_price": 43435,
    "price": 43435,
    "custom_code": "6GV59IS0AR9U1DEIO2NLB",
    "price_3d": 43435,
    "price_7d": 39595,
    "price_30d": 40875
  },
  {
    "id": "w21",
    "name_cn": "725双管霰弹枪",
    "name_en": "725 Shotgun",
    "type": "霰弹枪",
    "type_en": "Shotgun",
    "mode": "both",
    "base_stats": {
      "damage": 94,
      "rate_of_fire": 120,
      "accuracy": 32,
      "range": 30,
      "control": 52,
      "mobility": 84,
      "handling": 72
    },
    "ammo_type": [
      "12-gauge"
    ],
    "meta_tier": "S",
    "unlock_level": 1,
    "game_id": 446,
    "copy_count": 4697,
    "tags": [
      "S4新增",
      "双管"
    ],
    "loadout_price": 31915,
    "price": 31915,
    "custom_code": "6H2R61K08F8FFPMQA1O83",
    "price_3d": 31915,
    "price_7d": 31915,
    "price_30d": 31915
  },
  {
    "id": "w22",
    "name_cn": "M1014霰弹枪",
    "name_en": "M1014 Shotgun",
    "type": "霰弹枪",
    "type_en": "Shotgun",
    "mode": "both",
    "base_stats": {
      "damage": 88,
      "rate_of_fire": 200,
      "accuracy": 38,
      "range": 24,
      "control": 60,
      "mobility": 80,
      "handling": 72
    },
    "ammo_type": [
      "12-gauge"
    ],
    "meta_tier": "A",
    "unlock_level": 20,
    "game_id": 506,
    "copy_count": 4467,
    "tags": [
      "半自动"
    ],
    "loadout_price": 26588,
    "price": 26588,
    "custom_code": "6G9406008OPOB8QKQ72I8",
    "price_3d": 26588,
    "price_7d": 26588,
    "price_30d": 26588
  },
  {
    "id": "w23",
    "name_cn": "M16A4突击步枪",
    "name_en": "M16A4 AR",
    "type": "突击步枪",
    "type_en": "Assault Rifle",
    "mode": "warfare",
    "base_stats": {
      "damage": 70,
      "rate_of_fire": 700,
      "accuracy": 80,
      "range": 72,
      "control": 74,
      "mobility": 76,
      "handling": 72
    },
    "ammo_type": [
      "5.56"
    ],
    "meta_tier": "B",
    "unlock_level": 6,
    "game_id": 58,
    "copy_count": 594,
    "tags": [],
    "loadout_price": 12295,
    "price": 12295,
    "custom_code": "6GD1CM004J7LV61QLMNR9",
    "price_3d": 12295,
    "price_7d": 12295,
    "price_30d": 12295
  },
  {
    "id": "w24",
    "name_cn": "M4A1突击步枪",
    "name_en": "M4A1 AR",
    "type": "突击步枪",
    "type_en": "Assault Rifle",
    "mode": "both",
    "base_stats": {
      "damage": 68,
      "rate_of_fire": 800,
      "accuracy": 82,
      "range": 60,
      "control": 75,
      "mobility": 85,
      "handling": 80
    },
    "ammo_type": [
      "5.56"
    ],
    "meta_tier": "S",
    "unlock_level": 1,
    "game_id": 375,
    "copy_count": 1583,
    "tags": [
      "后坐力可控",
      "全能"
    ],
    "loadout_price": 129953,
    "price": 129953,
    "custom_code": "6G94AKO0FHI6PKF6C3P0U",
    "price_3d": 129953,
    "price_7d": 108288,
    "price_30d": 117573
  },
  {
    "id": "w25",
    "name_cn": "AUG突击步枪",
    "name_en": "AUG AR",
    "type": "突击步枪",
    "type_en": "Assault Rifle",
    "mode": "operations",
    "base_stats": {
      "damage": 74,
      "rate_of_fire": 780,
      "accuracy": 87,
      "range": 68,
      "control": 82,
      "mobility": 72,
      "handling": 78
    },
    "ammo_type": [
      "5.56"
    ],
    "meta_tier": "A",
    "unlock_level": 10,
    "game_id": 174,
    "copy_count": 3226,
    "tags": [
      "高精准",
      "危险行动"
    ],
    "loadout_price": 149854,
    "price": 149854,
    "custom_code": "6HFTMTK0EAR06C6UBJ9VT",
    "price_3d": 149854,
    "price_7d": 119254,
    "price_30d": 152914
  },
  {
    "id": "w26",
    "name_cn": "AKM突击步枪",
    "name_en": "AKM AR",
    "type": "突击步枪",
    "type_en": "Assault Rifle",
    "mode": "warfare",
    "base_stats": {
      "damage": 80,
      "rate_of_fire": 600,
      "accuracy": 65,
      "range": 75,
      "control": 60,
      "mobility": 70,
      "handling": 65
    },
    "ammo_type": [
      "5.56"
    ],
    "meta_tier": "A",
    "unlock_level": 5,
    "game_id": 241,
    "copy_count": 585,
    "tags": [
      "高爆发",
      "穿透力强"
    ],
    "loadout_price": 108157,
    "price": 108157,
    "custom_code": "6GRGLLS0FUH1E5MQ63E4O",
    "price_3d": 108157,
    "price_7d": 90127,
    "price_30d": 114167
  },
  {
    "id": "w27",
    "name_cn": "K416突击步枪",
    "name_en": "K416 AR",
    "type": "突击步枪",
    "type_en": "Assault Rifle",
    "mode": "warfare",
    "base_stats": {
      "damage": 70,
      "rate_of_fire": 780,
      "accuracy": 80,
      "range": 62,
      "control": 72,
      "mobility": 82,
      "handling": 78
    },
    "ammo_type": [
      "5.56"
    ],
    "meta_tier": "A",
    "unlock_level": 8,
    "game_id": 129,
    "copy_count": 1195,
    "tags": [
      "性价比高",
      "全兵种"
    ],
    "loadout_price": 164514,
    "price": 164514,
    "custom_code": "6GL0ARO0B47DBPRUAR75R",
    "price_3d": 164514,
    "price_7d": 153894,
    "price_30d": 111414
  },
  {
    "id": "w28",
    "name_cn": "AK-12突击步枪",
    "name_en": "AK-12 AR",
    "type": "突击步枪",
    "type_en": "Assault Rifle",
    "mode": "warfare",
    "base_stats": {
      "damage": 73,
      "rate_of_fire": 750,
      "accuracy": 76,
      "range": 74,
      "control": 68,
      "mobility": 78,
      "handling": 74
    },
    "ammo_type": [
      "5.56"
    ],
    "meta_tier": "A",
    "unlock_level": 15,
    "game_id": 499,
    "copy_count": 2196,
    "tags": [
      "版本强势"
    ],
    "loadout_price": 87387,
    "price": 87387,
    "custom_code": "6GE93140C56ME2PP5PQ4N",
    "price_3d": 87387,
    "price_7d": 75327,
    "price_30d": 99447
  },
  {
    "id": "w29",
    "name_cn": "AS Val突击步枪",
    "name_en": "AS Val AR",
    "type": "突击步枪",
    "type_en": "Assault Rifle",
    "mode": "warfare",
    "base_stats": {
      "damage": 78,
      "rate_of_fire": 900,
      "accuracy": 60,
      "range": 45,
      "control": 55,
      "mobility": 85,
      "handling": 82
    },
    "ammo_type": [
      "5.56"
    ],
    "meta_tier": "B",
    "unlock_level": 20,
    "game_id": 329,
    "copy_count": 3798,
    "tags": [
      "高射速",
      "消音"
    ],
    "loadout_price": 214791,
    "price": 214791,
    "custom_code": "6GL0C5O094898G9NDDGRT",
    "price_3d": 214791,
    "price_7d": 172871,
    "price_30d": 172871
  },
  {
    "id": "w30",
    "name_cn": "CAR-15突击步枪",
    "name_en": "CAR-15 AR",
    "type": "突击步枪",
    "type_en": "Assault Rifle",
    "mode": "both",
    "base_stats": {
      "damage": 66,
      "rate_of_fire": 850,
      "accuracy": 72,
      "range": 55,
      "control": 70,
      "mobility": 88,
      "handling": 85
    },
    "ammo_type": [
      "5.56"
    ],
    "meta_tier": "B",
    "unlock_level": 12,
    "game_id": 175,
    "copy_count": 4583,
    "tags": [],
    "loadout_price": 12304,
    "price": 12304,
    "custom_code": "6HH7K7K024CH4QGG5QQUE",
    "price_3d": 12304,
    "price_7d": 10768,
    "price_30d": 12313
  },
  {
    "id": "w31",
    "name_cn": "QBZ95-1突击步枪",
    "name_en": "QBZ-95-1 AR",
    "type": "突击步枪",
    "type_en": "Assault Rifle",
    "mode": "both",
    "base_stats": {
      "damage": 72,
      "rate_of_fire": 700,
      "accuracy": 76,
      "range": 72,
      "control": 68,
      "mobility": 74,
      "handling": 70
    },
    "ammo_type": [
      "5.56"
    ],
    "meta_tier": "A",
    "unlock_level": 10,
    "game_id": 429,
    "copy_count": 4903,
    "tags": [
      "S4增强",
      "国产"
    ],
    "loadout_price": 38843,
    "price": 38843,
    "custom_code": "6IG61OK0AGKBQQUCGH41Q",
    "price_3d": 38843,
    "price_7d": 38843,
    "price_30d": 38843
  },
  {
    "id": "w32",
    "name_cn": "AKS-74U突击步枪",
    "name_en": "AKS-74U AR",
    "type": "突击步枪",
    "type_en": "Assault Rifle",
    "mode": "both",
    "base_stats": {
      "damage": 68,
      "rate_of_fire": 680,
      "accuracy": 68,
      "range": 58,
      "control": 65,
      "mobility": 84,
      "handling": 78
    },
    "ammo_type": [
      "5.56"
    ],
    "meta_tier": "B",
    "unlock_level": 5,
    "game_id": 445,
    "copy_count": 3263,
    "tags": [
      "短管",
      "突击兵"
    ],
    "loadout_price": 12058,
    "price": 12058,
    "custom_code": "6GRTB7002GFSJ497HHJD0",
    "price_3d": 12058,
    "price_7d": 12058,
    "price_30d": 12068
  },
  {
    "id": "w33",
    "name_cn": "PTR-32突击步枪",
    "name_en": "PTR-32 AR",
    "type": "突击步枪",
    "type_en": "Assault Rifle",
    "mode": "warfare",
    "base_stats": {
      "damage": 65,
      "rate_of_fire": 850,
      "accuracy": 70,
      "range": 52,
      "control": 68,
      "mobility": 82,
      "handling": 78
    },
    "ammo_type": [
      "5.56"
    ],
    "meta_tier": "B",
    "unlock_level": 18,
    "game_id": 273,
    "copy_count": 4730,
    "tags": [],
    "loadout_price": 38228,
    "price": 38228,
    "custom_code": "6H01T1K09MTF0NSTEEU37",
    "price_3d": 38228,
    "price_7d": 38228,
    "price_30d": 38228
  },
  {
    "id": "w34",
    "name_cn": "SG552突击步枪",
    "name_en": "SG552 AR",
    "type": "突击步枪",
    "type_en": "Assault Rifle",
    "mode": "warfare",
    "base_stats": {
      "damage": 72,
      "rate_of_fire": 780,
      "accuracy": 78,
      "range": 66,
      "control": 70,
      "mobility": 76,
      "handling": 74
    },
    "ammo_type": [
      "5.56"
    ],
    "meta_tier": "B",
    "unlock_level": 16,
    "game_id": 314,
    "copy_count": 3744,
    "tags": [],
    "loadout_price": 39059,
    "price": 39059,
    "custom_code": "6G94APG0FHI6PKF6C3P0U",
    "price_3d": 39059,
    "price_7d": 39059,
    "price_30d": 45319
  },
  {
    "id": "w35",
    "name_cn": "腾龙突击步枪",
    "name_en": "Tenglong AR",
    "type": "突击步枪",
    "type_en": "Assault Rifle",
    "mode": "both",
    "base_stats": {
      "damage": 76,
      "rate_of_fire": 720,
      "accuracy": 80,
      "range": 70,
      "control": 72,
      "mobility": 74,
      "handling": 76
    },
    "ammo_type": [
      "5.56"
    ],
    "meta_tier": "A",
    "unlock_level": 20,
    "game_id": 206,
    "copy_count": 2225,
    "tags": [
      "S5新增"
    ],
    "loadout_price": 126187,
    "price": 126187,
    "custom_code": "6G1JN400AV5BVPK0VDMCD",
    "price_3d": 126187,
    "price_7d": 99142,
    "price_30d": 120177
  },
  {
    "id": "w36",
    "name_cn": "KC17突击步枪",
    "name_en": "KC17 AR",
    "type": "突击步枪",
    "type_en": "Assault Rifle",
    "mode": "warfare",
    "base_stats": {
      "damage": 74,
      "rate_of_fire": 760,
      "accuracy": 82,
      "range": 72,
      "control": 74,
      "mobility": 72,
      "handling": 76
    },
    "ammo_type": [
      "5.56"
    ],
    "meta_tier": "A",
    "unlock_level": 25,
    "game_id": 338,
    "copy_count": 1895,
    "tags": [
      "S5新增"
    ],
    "loadout_price": 151911,
    "price": 151911,
    "custom_code": "6HH8PD802AMR3AEE8LQVJ",
    "price_3d": 151911,
    "price_7d": 146671,
    "price_30d": 120471
  },
  {
    "id": "w37",
    "name_cn": "K437突击步枪",
    "name_en": "K437 AR",
    "type": "突击步枪",
    "type_en": "Assault Rifle",
    "mode": "both",
    "base_stats": {
      "damage": 74,
      "rate_of_fire": 780,
      "accuracy": 80,
      "range": 72,
      "control": 76,
      "mobility": 76,
      "handling": 72
    },
    "ammo_type": [
      "5.56"
    ],
    "meta_tier": "S",
    "unlock_level": 1,
    "game_id": 474,
    "copy_count": 2565,
    "tags": [
      "S4新增",
      "版本强势"
    ],
    "loadout_price": 117494,
    "price": 117494,
    "custom_code": "6JQ3PG00FKLSP2R6J3NCE",
    "price_3d": 117494,
    "price_7d": 106804,
    "price_30d": 106804
  },
  {
    "id": "w38",
    "name_cn": "M7突击步枪",
    "name_en": "M7 Battle Rifle",
    "type": "突击步枪",
    "type_en": "Assault Rifle",
    "mode": "both",
    "base_stats": {
      "damage": 85,
      "rate_of_fire": 450,
      "accuracy": 78,
      "range": 80,
      "control": 68,
      "mobility": 65,
      "handling": 70
    },
    "ammo_type": [
      "7.62"
    ],
    "meta_tier": "A",
    "unlock_level": 18,
    "game_id": 181,
    "copy_count": 1903,
    "tags": [
      "高性价比",
      "危险行动"
    ],
    "loadout_price": 203014,
    "price": 203014,
    "custom_code": "6I32ADK0195JPE5VK38LR",
    "price_3d": 203014,
    "price_7d": 165599,
    "price_30d": 197669
  },
  {
    "id": "w39",
    "name_cn": "SCAR-H突击步枪",
    "name_en": "SCAR-H BR",
    "type": "突击步枪",
    "type_en": "Assault Rifle",
    "mode": "operations",
    "base_stats": {
      "damage": 82,
      "rate_of_fire": 520,
      "accuracy": 76,
      "range": 82,
      "control": 68,
      "mobility": 62,
      "handling": 68
    },
    "ammo_type": [
      "7.62"
    ],
    "meta_tier": "A",
    "unlock_level": 26,
    "game_id": 79,
    "copy_count": 2943,
    "tags": [
      "新手友好",
      "高稳定性"
    ],
    "loadout_price": 96310,
    "price": 96310,
    "custom_code": "6HITGQK01RBVGS0BGKPDN",
    "price_3d": 96310,
    "price_7d": 75240,
    "price_30d": 96310
  },
  {
    "id": "w40",
    "name_cn": "ASh-12突击步枪",
    "name_en": "ASh-12 BR",
    "type": "突击步枪",
    "type_en": "Assault Rifle",
    "mode": "both",
    "base_stats": {
      "damage": 90,
      "rate_of_fire": 480,
      "accuracy": 68,
      "range": 75,
      "control": 60,
      "mobility": 58,
      "handling": 62
    },
    "ammo_type": [
      "7.62"
    ],
    "meta_tier": "S",
    "unlock_level": 30,
    "game_id": 495,
    "copy_count": 2884,
    "tags": [
      "大口径",
      "全兵种"
    ],
    "loadout_price": 186656,
    "price": 186656,
    "custom_code": "6GE37N00EA3FRKHMS9J6U",
    "price_3d": 186656,
    "price_7d": 154646,
    "price_30d": 143976
  },
  {
    "id": "w41",
    "name_cn": "G3突击步枪",
    "name_en": "G3 BR",
    "type": "突击步枪",
    "type_en": "Assault Rifle",
    "mode": "both",
    "base_stats": {
      "damage": 82,
      "rate_of_fire": 480,
      "accuracy": 72,
      "range": 80,
      "control": 64,
      "mobility": 58,
      "handling": 64
    },
    "ammo_type": [
      "7.62"
    ],
    "meta_tier": "B",
    "unlock_level": 22,
    "game_id": 527,
    "copy_count": 1192,
    "tags": [
      "经典DMR"
    ],
    "loadout_price": 54707,
    "price": 54707,
    "custom_code": "6H09U3K0C4V15L1N4PQQG",
    "price_3d": 54707,
    "price_7d": 51577,
    "price_30d": 59402
  },
  {
    "id": "w42",
    "name_cn": "MK47突击步枪",
    "name_en": "MK47 BR",
    "type": "突击步枪",
    "type_en": "Assault Rifle",
    "mode": "both",
    "base_stats": {
      "damage": 80,
      "rate_of_fire": 550,
      "accuracy": 75,
      "range": 78,
      "control": 65,
      "mobility": 68,
      "handling": 70
    },
    "ammo_type": [
      "7.62"
    ],
    "meta_tier": "B",
    "unlock_level": 25,
    "game_id": 1179,
    "copy_count": 3861,
    "tags": [
      "S5新增"
    ],
    "loadout_price": 154646,
    "price": 154646,
    "custom_code": "6HK8FU807G8S9A1C445HN",
    "price_3d": 154646,
    "price_7d": 127971,
    "price_30d": 111966
  },
  {
    "id": "w43",
    "name_cn": "杠杆式步枪",
    "name_en": "Lever Action Rifle",
    "type": "突击步枪",
    "type_en": "Assault Rifle",
    "mode": "both",
    "base_stats": {
      "damage": 78,
      "rate_of_fire": 300,
      "accuracy": 74,
      "range": 82,
      "control": 62,
      "mobility": 60,
      "handling": 64
    },
    "ammo_type": [
      "7.62"
    ],
    "meta_tier": "A",
    "unlock_level": 35,
    "game_id": 1180,
    "copy_count": 4301,
    "tags": [
      "S5新增",
      "西部风格"
    ],
    "loadout_price": 62295,
    "price": 62295,
    "custom_code": "6HJ5BG80FR6AJQIFQKVE3",
    "price_3d": 62295,
    "price_7d": 57735,
    "price_30d": 72935
  },
  {
    "id": "w44",
    "name_cn": "M14射手步枪",
    "name_en": "M14 DMR",
    "type": "射手步枪",
    "type_en": "DMR",
    "mode": "operations",
    "base_stats": {
      "damage": 82,
      "rate_of_fire": 500,
      "accuracy": 88,
      "range": 85,
      "control": 77,
      "mobility": 60,
      "handling": 70
    },
    "ammo_type": [
      "7.62"
    ],
    "meta_tier": "A",
    "unlock_level": 14,
    "game_id": 358,
    "copy_count": 1691,
    "tags": [
      "高稳定性",
      "远距离"
    ],
    "loadout_price": 131850,
    "price": 131850,
    "custom_code": "6GTTAT000CR1N4NF83220",
    "price_3d": 131850,
    "price_7d": 116025,
    "price_30d": 184600
  },
  {
    "id": "w45",
    "name_cn": "Mini-14射手步枪",
    "name_en": "Mini-14 DMR",
    "type": "射手步枪",
    "type_en": "DMR",
    "mode": "warfare",
    "base_stats": {
      "damage": 65,
      "rate_of_fire": 750,
      "accuracy": 90,
      "range": 88,
      "control": 82,
      "mobility": 70,
      "handling": 85
    },
    "ammo_type": [
      "7.62"
    ],
    "meta_tier": "A",
    "unlock_level": 16,
    "game_id": 217,
    "copy_count": 308,
    "tags": [
      "高稳定性",
      "远距离"
    ],
    "loadout_price": 38298,
    "price": 38298,
    "custom_code": "6I8VVA80ASAH8NM367QOA",
    "price_3d": 38298,
    "price_7d": 39093,
    "price_30d": 36928
  },
  {
    "id": "w46",
    "name_cn": "SR-25射手步枪",
    "name_en": "SR-25 DMR",
    "type": "射手步枪",
    "type_en": "DMR",
    "mode": "both",
    "base_stats": {
      "damage": 78,
      "rate_of_fire": 600,
      "accuracy": 88,
      "range": 90,
      "control": 76,
      "mobility": 62,
      "handling": 65
    },
    "ammo_type": [
      "7.62"
    ],
    "meta_tier": "S",
    "unlock_level": 30,
    "game_id": 579,
    "copy_count": 3238,
    "tags": [
      "高精准",
      "中远距离"
    ],
    "loadout_price": 208163,
    "price": 208163,
    "custom_code": "6GRAP2S0AV5BVPK0VDMCD",
    "price_3d": 208163,
    "price_7d": 176933,
    "price_30d": 156113
  },
  {
    "id": "w47",
    "name_cn": "SVD射手步枪",
    "name_en": "SVD DMR",
    "type": "射手步枪",
    "type_en": "DMR",
    "mode": "warfare",
    "base_stats": {
      "damage": 80,
      "rate_of_fire": 550,
      "accuracy": 85,
      "range": 88,
      "control": 70,
      "mobility": 58,
      "handling": 62
    },
    "ammo_type": [
      "7.62"
    ],
    "meta_tier": "A",
    "unlock_level": 25,
    "game_id": 395,
    "copy_count": 1382,
    "tags": [
      "经典DMR",
      "全兵种"
    ],
    "loadout_price": 135000,
    "price": 135000,
    "custom_code": "6GS5BGK064FJ19C5SGDFD",
    "price_3d": 135000,
    "price_7d": 126900,
    "price_30d": 113400
  },
  {
    "id": "w48",
    "name_cn": "VSS射手步枪",
    "name_en": "VSS DMR",
    "type": "射手步枪",
    "type_en": "DMR",
    "mode": "warfare",
    "base_stats": {
      "damage": 68,
      "rate_of_fire": 850,
      "accuracy": 72,
      "range": 55,
      "control": 65,
      "mobility": 82,
      "handling": 80
    },
    "ammo_type": [
      "7.62"
    ],
    "meta_tier": "B",
    "unlock_level": 32,
    "game_id": 80,
    "copy_count": 290,
    "tags": [
      "消音"
    ],
    "loadout_price": 46813,
    "price": 46813,
    "custom_code": "6JAPRKC024JT398JLMEUF",
    "price_3d": 46813,
    "price_7d": 46813,
    "price_30d": 48488
  },
  {
    "id": "w50",
    "name_cn": "PSG-1射手步枪",
    "name_en": "PSG-1 DMR",
    "type": "射手步枪",
    "type_en": "DMR",
    "mode": "warfare",
    "base_stats": {
      "damage": 88,
      "rate_of_fire": 380,
      "accuracy": 92,
      "range": 92,
      "control": 82,
      "mobility": 50,
      "handling": 58
    },
    "ammo_type": [
      "7.62"
    ],
    "meta_tier": "A",
    "unlock_level": 28,
    "game_id": 187,
    "copy_count": 4998,
    "tags": [
      "半自动狙击"
    ],
    "loadout_price": 118800,
    "price": 118800,
    "custom_code": "6H07HIO06GA8AHGUVS95M",
    "price_3d": 118800,
    "price_7d": 110700,
    "price_30d": 170100
  },
  {
    "id": "w51",
    "name_cn": "SKS射手步枪",
    "name_en": "SKS DMR",
    "type": "射手步枪",
    "type_en": "DMR",
    "mode": "warfare",
    "base_stats": {
      "damage": 72,
      "rate_of_fire": 480,
      "accuracy": 84,
      "range": 85,
      "control": 75,
      "mobility": 62,
      "handling": 68
    },
    "ammo_type": [
      "7.62"
    ],
    "meta_tier": "B",
    "unlock_level": 20,
    "game_id": 523,
    "copy_count": 1396,
    "tags": [
      "经典"
    ],
    "loadout_price": 47520,
    "price": 47520,
    "custom_code": "6FEHRUO0AV5BVPK0VDMCD",
    "price_3d": 47520,
    "price_7d": 43560,
    "price_30d": 53460
  },
  {
    "id": "w52",
    "name_cn": "SV-98狙击步枪",
    "name_en": "SV-98 Sniper",
    "type": "狙击步枪",
    "type_en": "Sniper Rifle",
    "mode": "warfare",
    "base_stats": {
      "damage": 95,
      "rate_of_fire": 45,
      "accuracy": 95,
      "range": 100,
      "control": 88,
      "mobility": 50,
      "handling": 55
    },
    "ammo_type": [
      "7.62"
    ],
    "meta_tier": "A",
    "unlock_level": 25,
    "game_id": 511,
    "copy_count": 4850,
    "tags": [],
    "loadout_price": 80535,
    "price": 80535,
    "custom_code": "6G940IC08OPOB8QKQ72I8",
    "price_3d": 80535,
    "price_7d": 74455,
    "price_30d": 82055
  },
  {
    "id": "w53",
    "name_cn": "AWM狙击步枪",
    "name_en": "AWM Sniper",
    "type": "狙击步枪",
    "type_en": "Sniper Rifle",
    "mode": "warfare",
    "base_stats": {
      "damage": 100,
      "rate_of_fire": 40,
      "accuracy": 98,
      "range": 100,
      "control": 90,
      "mobility": 45,
      "handling": 50
    },
    "ammo_type": [
      ".300 Win Mag"
    ],
    "meta_tier": "S",
    "unlock_level": 35,
    "game_id": 406,
    "copy_count": 2381,
    "tags": [],
    "loadout_price": 779059,
    "price": 779059,
    "custom_code": "6G940L008OPOB8QKQ72I8",
    "price_3d": 779059,
    "price_7d": 741959,
    "price_30d": 779059
  },
  {
    "id": "w54",
    "name_cn": "R93狙击步枪",
    "name_en": "R93 Sniper",
    "type": "狙击步枪",
    "type_en": "Sniper Rifle",
    "mode": "warfare",
    "base_stats": {
      "damage": 90,
      "rate_of_fire": 50,
      "accuracy": 92,
      "range": 95,
      "control": 85,
      "mobility": 52,
      "handling": 58
    },
    "ammo_type": [
      "7.62"
    ],
    "meta_tier": "A",
    "unlock_level": 30,
    "game_id": 449,
    "copy_count": 5417,
    "tags": [],
    "loadout_price": 123000,
    "price": 123000,
    "custom_code": "6HG9MUK08KE3E5HTC891L",
    "price_3d": 123000,
    "price_7d": 114000,
    "price_30d": 204000
  },
  {
    "id": "w55",
    "name_cn": "M700狙击步枪",
    "name_en": "M700 Sniper",
    "type": "狙击步枪",
    "type_en": "Sniper Rifle",
    "mode": "warfare",
    "base_stats": {
      "damage": 88,
      "rate_of_fire": 55,
      "accuracy": 94,
      "range": 96,
      "control": 86,
      "mobility": 52,
      "handling": 58
    },
    "ammo_type": [
      "7.62"
    ],
    "meta_tier": "A",
    "unlock_level": 28,
    "game_id": 225,
    "copy_count": 4388,
    "tags": [
      "栓动狙击"
    ],
    "loadout_price": 129000,
    "price": 129000,
    "custom_code": "6HBP2R0027UT3MNF433RH",
    "price_3d": 129000,
    "price_7d": 117000,
    "price_30d": 153000
  },
  {
    "id": "w56",
    "name_cn": "M249轻机枪",
    "name_en": "M249 LMG",
    "type": "轻机枪",
    "type_en": "Light Machine Gun",
    "mode": "both",
    "base_stats": {
      "damage": 72,
      "rate_of_fire": 850,
      "accuracy": 70,
      "range": 75,
      "control": 55,
      "mobility": 55,
      "handling": 50
    },
    "ammo_type": [
      "5.56"
    ],
    "meta_tier": "A",
    "unlock_level": 24,
    "game_id": 573,
    "copy_count": 2115,
    "tags": [
      "版本强势"
    ],
    "loadout_price": 97518,
    "price": 97518,
    "custom_code": "6G94JAC08OPOB8QKQ72I8",
    "price_3d": 97518,
    "price_7d": 70068,
    "price_30d": 192068
  },
  {
    "id": "w57",
    "name_cn": "QJB201轻机枪",
    "name_en": "QJB201 LMG",
    "type": "轻机枪",
    "type_en": "Light Machine Gun",
    "mode": "both",
    "base_stats": {
      "damage": 70,
      "rate_of_fire": 820,
      "accuracy": 72,
      "range": 76,
      "control": 56,
      "mobility": 54,
      "handling": 48
    },
    "ammo_type": [
      "5.56"
    ],
    "meta_tier": "A",
    "unlock_level": 26,
    "game_id": 134,
    "copy_count": 5585,
    "tags": [
      "国产",
      "全兵种"
    ],
    "loadout_price": 103353,
    "price": 103353,
    "custom_code": "6GQTJKO095HC4609S9G3Q",
    "price_3d": 103353,
    "price_7d": 75993,
    "price_30d": 118553
  },
  {
    "id": "w58",
    "name_cn": "M250通用机枪",
    "name_en": "M250 GMG",
    "type": "通用机枪",
    "type_en": "General Machine Gun",
    "mode": "warfare",
    "base_stats": {
      "damage": 68,
      "rate_of_fire": 800,
      "accuracy": 72,
      "range": 80,
      "control": 58,
      "mobility": 50,
      "handling": 38
    },
    "ammo_type": [
      "7.62"
    ],
    "meta_tier": "A",
    "unlock_level": 38,
    "game_id": 133,
    "copy_count": 3281,
    "tags": [
      "版本强势"
    ],
    "loadout_price": 261809,
    "price": 261809,
    "custom_code": "6GPHU14094898G9NDDGRT",
    "price_3d": 261809,
    "price_7d": 203014,
    "price_30d": 192324
  },
  {
    "id": "w59",
    "name_cn": "PKM通用机枪",
    "name_en": "PKM GMG",
    "type": "通用机枪",
    "type_en": "General Machine Gun",
    "mode": "warfare",
    "base_stats": {
      "damage": 75,
      "rate_of_fire": 780,
      "accuracy": 68,
      "range": 82,
      "control": 54,
      "mobility": 48,
      "handling": 40
    },
    "ammo_type": [
      "7.62"
    ],
    "meta_tier": "A",
    "unlock_level": 34,
    "game_id": 442,
    "copy_count": 3686,
    "tags": [
      "大口径"
    ],
    "loadout_price": 106393,
    "price": 106393,
    "custom_code": "6G94CVO0FHI6PKF6C3P0U",
    "price_3d": 106393,
    "price_7d": 75993,
    "price_30d": 88153
  },
  {
    "id": "w60",
    "name_cn": "复合弓",
    "name_en": "Compound Bow",
    "type": "特殊武器",
    "type_en": "Special",
    "mode": "both",
    "base_stats": {
      "damage": 95,
      "rate_of_fire": 60,
      "accuracy": 85,
      "range": 60,
      "control": 90,
      "mobility": 80,
      "handling": 75
    },
    "ammo_type": [
      "箭矢"
    ],
    "meta_tier": "S",
    "unlock_level": 1,
    "game_id": 71,
    "copy_count": 3914,
    "tags": [
      "近战",
      "一箭秒杀"
    ],
    "loadout_price": 108000,
    "price": 108000,
    "custom_code": "6GPEAS80CQ9J5LUV083F9",
    "price_3d": 108000,
    "price_7d": 108000,
    "price_30d": 120000
  },
  {
    "id": "w63",
    "name_cn": "M82狙击步枪",
    "name_en": "M82 Sniper",
    "type": "狙击步枪",
    "type_en": "Sniper Rifle",
    "mode": "both",
    "base_stats": {
      "damage": 125,
      "rate_of_fire": 60,
      "accuracy": 92,
      "range": 100,
      "control": 85,
      "mobility": 40,
      "handling": 45
    },
    "ammo_type": [
      ".50 BMG"
    ],
    "meta_tier": "S",
    "unlock_level": 1,
    "game_id": 0,
    "copy_count": 0,
    "tags": [
      "反器材",
      "S9新增",
      "大口径"
    ],
    "loadout_price": 267079,
    "price": 267079,
    "custom_code": "6JTK8JO087KKF9T2HJCH4",
    "price_3d": 267079,
    "price_7d": 274499,
    "price_30d": 393219
  },
  {
    "id": "w64",
    "name_cn": "AR57突击步枪",
    "name_en": "AR57 AR",
    "type": "突击步枪",
    "type_en": "Assault Rifle",
    "mode": "both",
    "base_stats": {
      "damage": 58,
      "rate_of_fire": 900,
      "accuracy": 78,
      "range": 55,
      "control": 70,
      "mobility": 85,
      "handling": 82
    },
    "ammo_type": [
      "5.7x28mm"
    ],
    "meta_tier": "S",
    "unlock_level": 1,
    "game_id": 0,
    "copy_count": 0,
    "tags": [
      "S9新增",
      "高速弹药"
    ],
    "loadout_price": 149311,
    "price": 149311,
    "custom_code": "6JOB6N40D4KUUL8R5A9D9",
    "price_3d": 149311,
    "price_7d": 159981,
    "price_30d": 133306
  },
  {
    "id": "w65",
    "name_cn": "FS-12霰弹枪",
    "name_en": "FS-12 Shotgun",
    "type": "霰弹枪",
    "type_en": "Shotgun",
    "mode": "both",
    "base_stats": {
      "damage": 85,
      "rate_of_fire": 120,
      "accuracy": 55,
      "range": 25,
      "control": 60,
      "mobility": 70,
      "handling": 65
    },
    "ammo_type": [
      "12 Gauge"
    ],
    "meta_tier": "B",
    "unlock_level": 1,
    "game_id": 0,
    "copy_count": 0,
    "tags": [
      "S9新增"
    ],
    "loadout_price": 79380,
    "price": 79380,
    "custom_code": "6IUMT9S08T16JCU0J1S9V",
    "price_3d": 79380,
    "price_7d": 79380,
    "price_30d": 79380
  },
  {
    "id": "w66",
    "name_cn": "MCX LT突击步枪",
    "name_en": "MCX LT Assault Rifle",
    "type": "突击步枪",
    "type_en": "Assault Rifle",
    "mode": "both",
    "base_stats": {
      "damage": 68,
      "rate_of_fire": 800,
      "accuracy": 78,
      "range": 65,
      "control": 75,
      "mobility": 80,
      "handling": 78
    },
    "ammo_type": [
      "5.56"
    ],
    "meta_tier": "A",
    "unlock_level": 1,
    "game_id": 0,
    "copy_count": 0,
    "tags": [
      "S9新增"
    ],
    "loadout_price": 79474,
    "price": 79474,
    "custom_code": "6IV6SPG03GFRB8J9CH4VL",
    "price_3d": 79474,
    "price_7d": 64174,
    "price_30d": 79474
  },
  {
    "id": "w67",
    "name_cn": "MK4冲锋枪",
    "name_en": "MK4 Submachine Gun",
    "type": "冲锋枪",
    "type_en": "Submachine Gun",
    "mode": "both",
    "base_stats": {
      "damage": 52,
      "rate_of_fire": 950,
      "accuracy": 72,
      "range": 35,
      "control": 68,
      "mobility": 88,
      "handling": 85
    },
    "ammo_type": [
      "9mm"
    ],
    "meta_tier": "B",
    "unlock_level": 1,
    "game_id": 0,
    "copy_count": 0,
    "tags": [
      "S9新增"
    ],
    "loadout_price": 69633,
    "price": 69633,
    "custom_code": "6I6FFL806UPSRBSFIDPDC",
    "price_3d": 69633,
    "price_7d": 57513,
    "price_30d": 75693
  },
  {
    "id": "w49",
    "name_cn": "SR9射手步枪",
    "name_en": "SR9 DMR",
    "type": "射手步枪",
    "type_en": "DMR",
    "mode": "both",
    "base_stats": {
      "damage": 62,
      "rate_of_fire": 780,
      "accuracy": 84,
      "range": 82,
      "control": 78,
      "mobility": 68,
      "handling": 78
    },
    "ammo_type": [
      "7.62"
    ],
    "meta_tier": "B",
    "unlock_level": 12,
    "game_id": 340,
    "copy_count": 3588,
    "tags": [],
    "loadout_price": 11250,
    "price": 11250,
    "price_3d": 11250,
    "price_7d": 10800,
    "price_30d": 10800
  }
]